captest/__init__.py
captest/_version.py
captest/capdata.py
captest/columngroups.py
captest/io.py
captest/plotting.py
captest/prtest.py
captest/util.py
captest-0.13.1.dist-info/LICENSE.txt
captest-0.13.1.dist-info/METADATA
captest-0.13.1.dist-info/WHEEL
captest-0.13.1.dist-info/top_level.txt
captest-0.13.1.dist-info/RECORD
