Metadata-Version: 2.1
Name: captest
Version: 0.13.1
Summary: Framework and methods to facilitate photovoltaic facility capacity testing following ASTM E2848.
Home-page: http://github.com/bt-/pvcaptest
Author: Ben Taylor
Author-email: benjaming.taylor@gmail.com
License: MIT
Platform: any
Classifier: Programming Language :: Python :: 3
Classifier: Development Status :: 2 - Pre-Alpha
Classifier: Natural Language :: English
Classifier: Intended Audience :: Science/Research
Classifier: License :: OSI Approved :: MIT License
Classifier: Operating System :: OS Independent
Classifier: Topic :: Scientific/Engineering
Requires-Python: >=3.8
License-File: LICENSE.txt
Requires-Dist: pandas >=1
Requires-Dist: numpy >=1.13.0
Requires-Dist: python-dateutil >=2.5
Requires-Dist: matplotlib >=2
Requires-Dist: statsmodels >=0.8
Requires-Dist: scikit-learn >=0.19
Requires-Dist: bokeh >=3.0.0
Requires-Dist: colorcet
Requires-Dist: param
Provides-Extra: all
Requires-Dist: build ; extra == 'all'
Requires-Dist: coveralls ; extra == 'all'
Requires-Dist: docutils ==0.18.1 ; extra == 'all'
Requires-Dist: holoviews >=1.14.8 ; extra == 'all'
Requires-Dist: nbsphinx ==0.9.1 ; extra == 'all'
Requires-Dist: notebook ; extra == 'all'
Requires-Dist: openpyxl ; extra == 'all'
Requires-Dist: panel ; extra == 'all'
Requires-Dist: pvlib >=0.9.0 ; extra == 'all'
Requires-Dist: pytest ; extra == 'all'
Requires-Dist: pytest-cov ; extra == 'all'
Requires-Dist: pytest-mock ; extra == 'all'
Requires-Dist: pytest-timeout ; extra == 'all'
Requires-Dist: recommonmark ==0.7.1 ; extra == 'all'
Requires-Dist: sphinx ==6.1.3 ; extra == 'all'
Requires-Dist: sphinx-rtd-theme ==1.2.0 ; extra == 'all'
Requires-Dist: twine ; extra == 'all'
Provides-Extra: build
Requires-Dist: holoviews >=1.14.8 ; extra == 'build'
Requires-Dist: panel ; extra == 'build'
Requires-Dist: pvlib >=0.9.0 ; extra == 'build'
Requires-Dist: openpyxl ; extra == 'build'
Requires-Dist: build ; extra == 'build'
Requires-Dist: twine ; extra == 'build'
Provides-Extra: docs
Requires-Dist: holoviews >=1.14.8 ; extra == 'docs'
Requires-Dist: panel ; extra == 'docs'
Requires-Dist: pvlib >=0.9.0 ; extra == 'docs'
Requires-Dist: openpyxl ; extra == 'docs'
Requires-Dist: docutils ==0.18.1 ; extra == 'docs'
Requires-Dist: nbsphinx ==0.9.1 ; extra == 'docs'
Requires-Dist: notebook ; extra == 'docs'
Requires-Dist: recommonmark ==0.7.1 ; extra == 'docs'
Requires-Dist: sphinx ==6.1.3 ; extra == 'docs'
Requires-Dist: sphinx-rtd-theme ==1.2.0 ; extra == 'docs'
Provides-Extra: optional
Requires-Dist: holoviews >=1.14.8 ; extra == 'optional'
Requires-Dist: panel ; extra == 'optional'
Requires-Dist: pvlib >=0.9.0 ; extra == 'optional'
Requires-Dist: openpyxl ; extra == 'optional'
Provides-Extra: test
Requires-Dist: holoviews >=1.14.8 ; extra == 'test'
Requires-Dist: panel ; extra == 'test'
Requires-Dist: pvlib >=0.9.0 ; extra == 'test'
Requires-Dist: openpyxl ; extra == 'test'
Requires-Dist: coveralls ; extra == 'test'
Requires-Dist: pytest ; extra == 'test'
Requires-Dist: pytest-cov ; extra == 'test'
Requires-Dist: pytest-mock ; extra == 'test'
Requires-Dist: pytest-timeout ; extra == 'test'
